seisflows/__init__.py
seisflows/seisflows.py
seisflows/examples/__init__.py
seisflows/examples/ex1_homogeneous_halfspace.py
seisflows/examples/ex2_hh_w_pyatoa.py
seisflows/examples/ex3_fwd_solver.py
seisflows/examples/sfexample2d.py
seisflows/optimize/LBFGS.py
seisflows/optimize/NLCG.py
seisflows/optimize/__init__.py
seisflows/optimize/gradient.py
seisflows/plugins/__init__.py
seisflows/plugins/line_search/__init__.py
seisflows/plugins/line_search/backtrack.py
seisflows/plugins/line_search/bracket.py
seisflows/plugins/preprocess/__init__.py
seisflows/plugins/preprocess/adjoint.py
seisflows/plugins/preprocess/misfit.py
seisflows/plugins/preprocess/wavelets.py
seisflows/preprocess/__init__.py
seisflows/preprocess/default.py
seisflows/preprocess/pyaflowa.py
seisflows/solver/__init__.py
seisflows/solver/specfem.py
seisflows/solver/specfem2d.py
seisflows/solver/specfem3d.py
seisflows/solver/specfem3d_globe.py
seisflows/system/__init__.py
seisflows/system/chinook.py
seisflows/system/cluster.py
seisflows/system/frontera.py
seisflows/system/fujitsu.py
seisflows/system/lsf.py
seisflows/system/maui.py
seisflows/system/singularity.py
seisflows/system/slurm.py
seisflows/system/wisteria.py
seisflows/system/workstation.py
seisflows/system/runscripts/__init__.py
seisflows/system/runscripts/run_funcs.py
seisflows/system/runscripts/submit_workflow.py
seisflows/tests/__init__.py
seisflows/tests/test_optimize.py
seisflows/tests/test_preprocess.py
seisflows/tests/test_seisflows.py
seisflows/tests/test_solver.py
seisflows/tests/test_system.py
seisflows/tests/test_tools.py
seisflows/tools/__init__.py
seisflows/tools/array.py
seisflows/tools/config.py
seisflows/tools/graphics.py
seisflows/tools/math.py
seisflows/tools/model.py
seisflows/tools/msg.py
seisflows/tools/signal.py
seisflows/tools/specfem.py
seisflows/tools/unix.py
seisflows/workflow/__init__.py
seisflows/workflow/forward.py
seisflows/workflow/inversion.py
seisflows/workflow/migration.py
seisflows/workflow/test_flow.py
seisflows-2.3.1.dist-info/LICENSE
seisflows-2.3.1.dist-info/METADATA
seisflows-2.3.1.dist-info/WHEEL
seisflows-2.3.1.dist-info/entry_points.txt
seisflows-2.3.1.dist-info/top_level.txt
seisflows-2.3.1.dist-info/RECORD
