Metadata-Version: 2.1
Name: seisflows
Version: 2.3.1
Summary: An automated workflow tool for full waveform inversion
Author: adjTomo Dev Team
Author-email: adjtomo@gmail.com
License: Copyright (c) 2014, Princeton University
Project-URL: homepage, https://github.com/adjtomo/
Project-URL: documentation, https://seisflows.readthedocs.io
Project-URL: repository, https://github.com/adjtomo/seisflows
Requires-Python: >=3.7
License-File: LICENSE
Requires-Dist: obspy
Requires-Dist: pyyaml
Requires-Dist: IPython
Requires-Dist: dill
Requires-Dist: pyatoa <=0.2.2
Requires-Dist: pysep-adjtomo <=0.4.1
Provides-Extra: dev
Requires-Dist: pytest ; extra == 'dev'
Requires-Dist: ipython ; extra == 'dev'
Requires-Dist: ipdb ; extra == 'dev'
